{
  "plugins": [
    {
      "loader": "java_plain",
      "id": "{project.name}",
      "name": "{rootProject.name}",
      "version": "{version}",
      "main-class": "xyz.jpenilla.minimotd.sponge8.MiniMOTDPlugin",
      "description": "{description}",
      "links": {
        "homepage": "{url}",
        "source": "{url}",
        "issues": "{url}issues"
      },
      "contributors": [
        {
          "name": "jmp",
          "description": "Lead Developer"
        }
      ],
      "dependencies": [
        {
          "id": "spongeapi",
          "version": "8.0.0"
        }
      ]
    }
  ]
}
